openwisp_radius/__init__.py
openwisp_radius/admin.py
openwisp_radius/apps.py
openwisp_radius/checks.py
openwisp_radius/coa.py
openwisp_radius/consumers.py
openwisp_radius/exceptions.py
openwisp_radius/models.py
openwisp_radius/receivers.py
openwisp_radius/registration.py
openwisp_radius/routing.py
openwisp_radius/settings.py
openwisp_radius/signals.py
openwisp_radius/tasks.py
openwisp_radius/urls.py
openwisp_radius/utils.py
openwisp_radius/api/__init__.py
openwisp_radius/api/exceptions.py
openwisp_radius/api/freeradius_views.py
openwisp_radius/api/permissions.py
openwisp_radius/api/serializers.py
openwisp_radius/api/swagger.py
openwisp_radius/api/urls.py
openwisp_radius/api/utils.py
openwisp_radius/api/views.py
openwisp_radius/base/__init__.py
openwisp_radius/base/admin_filters.py
openwisp_radius/base/forms.py
openwisp_radius/base/models.py
openwisp_radius/base/validators.py
openwisp_radius/counters/__init__.py
openwisp_radius/counters/base.py
openwisp_radius/counters/exceptions.py
openwisp_radius/counters/resets.py
openwisp_radius/counters/mysql/__init__.py
openwisp_radius/counters/mysql/daily_counter.py
openwisp_radius/counters/mysql/daily_traffic_counter.py
openwisp_radius/counters/mysql/monthly_traffic_counter.py
openwisp_radius/counters/postgresql/__init__.py
openwisp_radius/counters/postgresql/daily_counter.py
openwisp_radius/counters/postgresql/daily_traffic_counter.py
openwisp_radius/counters/postgresql/monthly_traffic_counter.py
openwisp_radius/counters/sqlite/__init__.py
openwisp_radius/counters/sqlite/daily_counter.py
openwisp_radius/counters/sqlite/daily_traffic_counter.py
openwisp_radius/counters/sqlite/monthly_traffic_counter.py
openwisp_radius/integrations/__init__.py
openwisp_radius/integrations/monitoring/__init__.py
openwisp_radius/integrations/monitoring/admin.py
openwisp_radius/integrations/monitoring/apps.py
openwisp_radius/integrations/monitoring/configuration.py
openwisp_radius/integrations/monitoring/receivers.py
openwisp_radius-1.2.dist-info/licenses/LICENSE
openwisp_radius-1.2.dist-info/METADATA
openwisp_radius-1.2.dist-info/WHEEL
openwisp_radius-1.2.dist-info/top_level.txt
openwisp_radius-1.2.dist-info/RECORD
