Metadata-Version: 2.4
Name: openwisp-radius
Version: 1.2
Summary: OpenWISP Radius
Home-page: https://openwisp.org
Download-URL: https://github.com/openwisp/openwisp-radius/releases
Author: OpenWISP
Author-email: support@openwisp.io
License: GPL3
Keywords: django,freeradius,networking,openwisp
Platform: Platform Independent
Classifier: Development Status :: 5 - Production/Stable
Classifier: Environment :: Web Environment
Classifier: Topic :: Internet :: WWW/HTTP
Classifier: Topic :: System :: Networking
Classifier: Intended Audience :: Developers
Classifier: License :: OSI Approved :: GNU General Public License v3 (GPLv3)
Classifier: Operating System :: OS Independent
Classifier: Framework :: Django
Classifier: Programming Language :: Python :: 3
License-File: LICENSE
Requires-Dist: openwisp-notifications~=1.2.0
Requires-Dist: openwisp-users~=1.2.0
Requires-Dist: openwisp-utils[celery,rest]~=1.2.0
Requires-Dist: passlib~=1.7.1
Requires-Dist: djangorestframework-link-header-pagination~=0.1.1
Requires-Dist: weasyprint<67,>=65
Requires-Dist: dj-rest-auth<7.1,>=6.0
Requires-Dist: django-sendsms~=0.5.0
Requires-Dist: jsonfield~=3.1.0
Requires-Dist: django-private-storage~=3.1.0
Requires-Dist: django-ipware<7.1,>=5.0
Requires-Dist: pyrad~=2.4
Requires-Dist: Exscript~=2.6.28
Provides-Extra: saml
Requires-Dist: djangosaml2==1.11.1; extra == "saml"
Provides-Extra: openvpn-status
Requires-Dist: openvpn-status~=0.2.1; extra == "openvpn-status"
Dynamic: author
Dynamic: author-email
Dynamic: classifier
Dynamic: description
Dynamic: download-url
Dynamic: home-page
Dynamic: keywords
Dynamic: license
Dynamic: license-file
Dynamic: platform
Dynamic: provides-extra
Dynamic: requires-dist
Dynamic: summary
